Cherrydoor-0.8.1.data/scripts/cherrydoor-install
cherrydoor/__init__.py
cherrydoor/__main__.py
cherrydoor/__version__.py
cherrydoor/api_tokens.py
cherrydoor/app.py
cherrydoor/auth.py
cherrydoor/config.py
cherrydoor/secure.py
cherrydoor/socketio.py
cherrydoor/util.py
cherrydoor/views.py
cherrydoor/api/__init__.py
cherrydoor/api/api_key_endpoint.py
cherrydoor/api/cards_endpoint.py
cherrydoor/api/door_endpoint.py
cherrydoor/api/find_user_endpoint.py
cherrydoor/api/manage_user_endpoint.py
cherrydoor/api/manage_users_endpoint.py
cherrydoor/api/stats_endpoint.py
cherrydoor/cli/__init__.py
cherrydoor/cli/install.py
cherrydoor/cli/update.py
cherrydoor/cli/update_scripts/__init__.py
cherrydoor/cli/update_scripts/aiohttp.py
cherrydoor/database/__init__.py
cherrydoor/database/mongo.py
cherrydoor/interface/__init__.py
cherrydoor/interface/serial.py
cherrydoor/static/components/Dashboard.js
cherrydoor/static/components/DoorStatus.js
cherrydoor/static/components/HamburgerMenu.js
cherrydoor/static/components/Header.js
cherrydoor/static/components/ManageUsers.js
cherrydoor/static/components/Navbar.js
cherrydoor/static/components/SerialConsole.js
cherrydoor/static/components/Settings-timepicker.js
cherrydoor/static/components/Settings.js
cherrydoor/static/components/UsageChart.js
cherrydoor/static/components/Users.js
cherrydoor/static/components/VueTimepicker.js
cherrydoor/static/components/v-shell.js
cherrydoor/static/css/all.css
cherrydoor/static/css/index.css
cherrydoor/static/css/inputs.css
cherrydoor/static/css/login.css
cherrydoor/static/css/materialize.min.css
cherrydoor/static/css/v-shell.css
cherrydoor/static/css/vue-timepicker.css
cherrydoor/static/fonts/Nunito/Nunito-Black.ttf
cherrydoor/static/fonts/Nunito/Nunito-BlackItalic.ttf
cherrydoor/static/fonts/Nunito/Nunito-Bold.ttf
cherrydoor/static/fonts/Nunito/Nunito-BoldItalic.ttf
cherrydoor/static/fonts/Nunito/Nunito-ExtraBold.ttf
cherrydoor/static/fonts/Nunito/Nunito-ExtraBoldItalic.ttf
Cherrydoor-0.8.1.dist-info/LICENSE
Cherrydoor-0.8.1.dist-info/METADATA
Cherrydoor-0.8.1.dist-info/WHEEL
Cherrydoor-0.8.1.dist-info/entry_points.txt
Cherrydoor-0.8.1.dist-info/top_level.txt
Cherrydoor-0.8.1.dist-info/RECORD
