Metadata-Version: 2.1
Name: Cherrydoor
Version: 0.8.1
Summary: An overengineered rfid lock manager created for my school community. Made for Raspberry Pi connected with another microcontroler that send and receieves rfid data via UART
Home-page: https://github.com/oplik0/cherrydoor
Author: oplik0
License: MIT
Keywords: wisniowasu mongodb flask rfid lock cherrydoor
Platform: UNKNOWN
Classifier: Development Status :: 3 - Alpha
Classifier: Intended Audience :: Education
Classifier: License :: OSI Approved :: MIT License
Classifier: Operating System :: POSIX :: Linux
Classifier: Programming Language :: Python :: 3
Classifier: Topic :: Home Automation
Classifier: Topic :: Terminals :: Serial
Classifier: Topic :: Internet :: WWW/HTTP
Requires-Python: >=3.9
License-File: LICENSE
Requires-Dist: aiohttp (==3.6.3)
Requires-Dist: aioserial (>=1.3)
Requires-Dist: argon2-cffi (>=19)
Requires-Dist: motor (>=2.1)
Requires-Dist: confuse (>=1.3)
Requires-Dist: pybranca (>=0.3)
Requires-Dist: msgpack (>=1.0)
Requires-Dist: aiohttp-csrf-fixed (>=0.0.3)
Requires-Dist: aiohttp-jinja2 (>=1.2)
Requires-Dist: aiohttp-rest-api-redoc (>=0.2.3)
Requires-Dist: aiohttp-security (>=0.4.0)
Requires-Dist: aiohttp-session (>=2.9.0)
Requires-Dist: aiohttp-session-mongo (>=0.0.1)
Requires-Dist: secure (>=0.3.0)
Requires-Dist: sentry-sdk (>=0.16.5)
Requires-Dist: packaging (>=20)
Requires-Dist: aiojobs (>=0.2.2)
Requires-Dist: python-socketio (>=4.6.0)
Provides-Extra: speedups
Requires-Dist: aiodns (>=1.1) ; extra == 'speedups'
Requires-Dist: Brotli ; extra == 'speedups'
Requires-Dist: cchardet ; extra == 'speedups'
Requires-Dist: uvloop (>=0.14) ; extra == 'speedups'
